amplify_qaoa/__init__.py
amplify_qaoa/__version__.py
amplify_qaoa/runners/__init__.py
amplify_qaoa/runners/core.py
amplify_qaoa/runners/qiskit_runner.py
amplify_qaoa/runners/qulacs_runner.py
amplify.qaoa-0.4.3.dist-info/LICENSE.txt
amplify.qaoa-0.4.3.dist-info/METADATA
amplify.qaoa-0.4.3.dist-info/WHEEL
amplify.qaoa-0.4.3.dist-info/top_level.txt
amplify.qaoa-0.4.3.dist-info/RECORD
