Metadata-Version: 2.1
Name: amplify.qaoa
Version: 0.4.3
Summary: Amplify SDK for running QAOA with quantum computer and simulator
Author: Kanto Teranishi
Author-email: kanto.teranishi@fixstars.com
Keywords: sdk,QAOA,quantum,QUBO,quadratic unconstrained binary optimization,Ising model,fixstars
Classifier: Environment :: Console
Classifier: Development Status :: 4 - Beta
Classifier: License :: OSI Approved :: Apache Software License
Classifier: Intended Audience :: Developers
Classifier: Intended Audience :: Science/Research
Classifier: Topic :: Software Development :: Libraries :: Python Modules
Classifier: Topic :: Scientific/Engineering
Classifier: Programming Language :: Python :: 3.8
Classifier: Programming Language :: Python :: 3.9
Classifier: Programming Language :: Python :: 3.10
Classifier: Programming Language :: Python :: 3.11
Requires-Python: >=3.8
License-File: LICENSE.txt
Requires-Dist: qiskit
Requires-Dist: qiskit-aer !=0.13.0
Requires-Dist: qiskit-ibm-provider !=0.5.3
Requires-Dist: qulacs
